xlson/__init__.py
xlson/constants.py
xlson/formatting.py
xlson/xl2html.py
xlson/xl_preparation.py
xlson/xl_to_html.py
xlson/_lib/__init__.py
xlson/_lib/coords_tools.py
xlson/_lib/general_utils.py
xlson/_lib/obj_tools.py
xlson/handlers/__init__.py
xlson/handlers/xlson_handler.py
xlson/scheme/__init__.py
xlson/scheme/setup_xlson.py
xlson/tests/__init__.py
xlson/tests/test_lib.py
xlson/tests/test_xlson.py
xlson-0.1.0.dist-info/LICENSE
xlson-0.1.0.dist-info/METADATA
xlson-0.1.0.dist-info/WHEEL
xlson-0.1.0.dist-info/entry_points.txt
xlson-0.1.0.dist-info/top_level.txt
xlson-0.1.0.dist-info/RECORD
